vmcompact/__init__.py
vmcompact/app.py
vmcompact/banner.py
vmcompact/builders.py
vmcompact/channels.py
vmcompact/config.py
vmcompact/configurations.py
vmcompact/data.py
vmcompact/errors.py
vmcompact/gainlayer.py
vmcompact/gui/banana/__init__.py
vmcompact/gui/banana/main.py
vmcompact/gui/basic/__init__.py
vmcompact/gui/basic/main.py
vmcompact/gui/potato/__init__.py
vmcompact/gui/potato/main.py
vmcompact/img/cat.ico
vmcompact/menu.py
vmcompact/navigation.py
vmcompact/subject.py
voicemeeter_compact-1.9.8.dist-info/entry_points.txt
voicemeeter_compact-1.9.8.dist-info/LICENSE
voicemeeter_compact-1.9.8.dist-info/METADATA
voicemeeter_compact-1.9.8.dist-info/WHEEL
voicemeeter_compact-1.9.8.dist-info/RECORD
