Metadata-Version: 2.3
Name: voicemeeter-compact
Version: 1.9.8
Summary: A Compact Voicemeeter Remote App
License: MIT
Author: Onyx and Iris
Author-email: code@onyxandiris.online
Requires-Python: >=3.10,<3.14
Classifier: License :: OSI Approved :: MIT License
Classifier: Programming Language :: Python :: 3
Classifier: Programming Language :: Python :: 3.10
Classifier: Programming Language :: Python :: 3.11
Classifier: Programming Language :: Python :: 3.12
Classifier: Programming Language :: Python :: 3.13
Requires-Dist: sv-ttk (>=2.6.0,<3.0.0)
Requires-Dist: tomli (>=2.0.1,<3.0) ; python_version < "3.11"
Requires-Dist: vban-cmd (>=2.5.0,<3.0.0)
Requires-Dist: voicemeeter-api (>=2.6.1,<3.0.0)
